{
    "parent": "good_nights_sleep:nightmare/obtain_zitrite_ingot",
    "display": {
        "icon": {
            "item": "good_nights_sleep:zitrite_sword"
        },
        "title": {
            "translate": "advancements.good_nights_sleep.obtain_zitrite_sword.title"
        },
        "description": {
            "translate": "advancements.good_nights_sleep.obtain_zitrite_sword.desc"
        }
    },
    "criteria": {
        "have_item": {
            "trigger": "minecraft:inventory_changed",
            "conditions": {
                "items": [
                    {
                        "item": "good_nights_sleep:zitrite_sword"
                    }
                ]
            }
        }
    }
}